{
  "classname": null,
  "name": null,
  "animation": {
    "classname": null,
    "name": "AnimationManager",
    "actionlist": []
  },
  "dataScale": 1,
  "designHeight": 640,
  "designWidth": 1136,
  "textures": [],
  "texturesPng": [],
  "version": "1.6.0.0",
  "widgetTree": {
    "classname": "Panel",
    "name": null,
    "children": [
      {
        "classname": "ImageView",
        "name": null,
        "children": [
          {
            "classname": "Label",
            "name": null,
            "children": [],
            "options": {
              "__type": "LabelSurrogate:#EditorCommon.JsonModel.Component.GUI",
              "classname": "Label",
              "name": "Label_title",
              "ZOrder": 0,
              "actiontag": 3232504,
              "anchorPointX": 0.5,
              "anchorPointY": 0.5,
              "classType": "CocoStudio.EngineAdapterWrap.CSLabel",
              "colorB": 255,
              "colorG": 255,
              "colorR": 255,
              "customProperty": "",
              "flipX": false,
              "flipY": false,
              "height": 33,
              "ignoreSize": true,
              "layoutParameter": null,
              "opacity": 255,
              "positionPercentX": 0,
              "positionPercentY": 0.434937626,
              "positionType": 0,
              "rotation": 0,
              "scaleX": 1,
              "scaleY": 1,
              "sizePercentX": 0.0695652142,
              "sizePercentY": 0.05882353,
              "sizeType": 0,
              "tag": 1091625,
              "touchAble": false,
              "useMergedTexture": false,
              "visible": true,
              "width": 64,
              "x": 0,
              "y": 244,
              "areaHeight": 0,
              "areaWidth": 0,
              "fontFile": null,
              "fontName": "static/FZCuYuan-M03S.ttf",
              "fontSize": 32,
              "hAlignment": 1,
              "text": "标题",
              "touchScaleEnable": false,
              "vAlignment": 1
            }
          },
          {
            "classname": "Button",
            "name": null,
            "children": [],
            "options": {
              "__type": "ButtonSurrogate:#EditorCommon.JsonModel.Component.GUI",
              "classname": "Button",
              "name": "Button_close",
              "ZOrder": 5,
              "actiontag": 56800691,
              "anchorPointX": 0.5,
              "anchorPointY": 0.5,
              "classType": "CocoStudio.EngineAdapterWrap.CSButton",
              "colorB": 255,
              "colorG": 255,
              "colorR": 255,
              "customProperty": "",
              "flipX": false,
              "flipY": false,
              "height": 49,
              "ignoreSize": true,
              "layoutParameter": null,
              "opacity": 255,
              "positionPercentX": 0.452173918,
              "positionPercentY": 0.424242437,
              "positionType": 0,
              "rotation": 0,
              "scaleX": 1,
              "scaleY": 1,
              "sizePercentX": 0.05326087,
              "sizePercentY": 0.08734403,
              "sizeType": 0,
              "tag": 1091513,
              "touchAble": true,
              "useMergedTexture": false,
              "visible": true,
              "width": 49,
              "x": 416,
              "y": 238,
              "capInsetsHeight": 1,
              "capInsetsWidth": 1,
              "capInsetsX": 0,
              "capInsetsY": 0,
              "disabled": null,
              "disabledData": {
                "path": "activity/X悬赏/切图/bth_xuanshang_zhujiemian_tanchuang_normal.png",
                "plistFile": "",
                "resourceType": 0
              },
              "fontName": "微软雅黑",
              "fontSize": 14,
              "fontType": 0,
              "normal": null,
              "normalData": {
                "path": "activity/X悬赏/切图/bth_xuanshang_zhujiemian_tanchuang_normal.png",
                "plistFile": "",
                "resourceType": 0
              },
              "pressed": null,
              "pressedData": {
                "path": "activity/X悬赏/切图/bth_xuanshang_zhujiemian_tanchuang_press.png",
                "plistFile": "",
                "resourceType": 0
              },
              "scale9Enable": false,
              "scale9Height": 49,
              "scale9Width": 49,
              "text": "",
              "textColorB": 255,
              "textColorG": 255,
              "textColorR": 255
            }
          },
          {
            "classname": "Panel",
            "name": null,
            "children": [],
            "options": {
              "__type": "PanelSurrogate:#EditorCommon.JsonModel.Component.GUI",
              "classname": "Panel",
              "name": "Panel_heroList",
              "ZOrder": 2,
              "actiontag": 52697618,
              "anchorPointX": 0.5,
              "anchorPointY": 0,
              "classType": "CocoStudio.EngineAdapterWrap.CSPanel",
              "colorB": 255,
              "colorG": 255,
              "colorR": 255,
              "customProperty": "",
              "flipX": false,
              "flipY": false,
              "height": 438,
              "ignoreSize": false,
              "layoutParameter": null,
              "opacity": 255,
              "positionPercentX": -0.229347825,
              "positionPercentY": -0.402852058,
              "positionType": 0,
              "rotation": 0,
              "scaleX": 1,
              "scaleY": 1,
              "sizePercentX": 0.454347819,
              "sizePercentY": 0.780748665,
              "sizeType": 0,
              "tag": 1090703,
              "touchAble": true,
              "useMergedTexture": false,
              "visible": true,
              "width": 418,
              "x": -211,
              "y": -226,
              "adaptScreen": false,
              "backGroundImage": null,
              "backGroundImageData": null,
              "backGroundScale9Enable": false,
              "bgColorB": 255,
              "bgColorG": 200,
              "bgColorOpacity": 0,
              "bgColorR": 150,
              "bgEndColorB": 255,
              "bgEndColorG": 200,
              "bgEndColorR": 150,
              "bgStartColorB": 255,
              "bgStartColorG": 255,
              "bgStartColorR": 255,
              "capInsetsHeight": 1,
              "capInsetsWidth": 1,
              "capInsetsX": 0,
              "capInsetsY": 0,
              "clipAble": false,
              "colorType": 1,
              "layoutType": 0,
              "vectorX": 0,
              "vectorY": -0.5
            }
          },
          {
            "classname": "ImageView",
            "name": null,
            "children": [
              {
                "classname": "Panel",
                "name": null,
                "children": [],
                "options": {
                  "__type": "PanelSurrogate:#EditorCommon.JsonModel.Component.GUI",
                  "classname": "Panel",
                  "name": "Panel_icon",
                  "ZOrder": 0,
                  "actiontag": 44227114,
                  "anchorPointX": 0,
                  "anchorPointY": 1,
                  "classType": "CocoStudio.EngineAdapterWrap.CSPanel",
                  "colorB": 255,
                  "colorG": 255,
                  "colorR": 255,
                  "customProperty": "",
                  "flipX": false,
                  "flipY": false,
                  "height": 70,
                  "ignoreSize": false,
                  "layoutParameter": null,
                  "opacity": 255,
                  "positionPercentX": -0.45433256,
                  "positionPercentY": 0.3090909,
                  "positionType": 0,
                  "rotation": 0,
                  "scaleX": 1,
                  "scaleY": 1,
                  "sizePercentX": 0.163934425,
                  "sizePercentY": 0.6363636,
                  "sizeType": 0,
                  "tag": 1089543,
                  "touchAble": true,
                  "useMergedTexture": false,
                  "visible": true,
                  "width": 70,
                  "x": -194,
                  "y": 34,
                  "adaptScreen": false,
                  "backGroundImage": null,
                  "backGroundImageData": null,
                  "backGroundScale9Enable": false,
                  "bgColorB": 255,
                  "bgColorG": 200,
                  "bgColorOpacity": 0,
                  "bgColorR": 150,
                  "bgEndColorB": 255,
                  "bgEndColorG": 200,
                  "bgEndColorR": 150,
                  "bgStartColorB": 255,
                  "bgStartColorG": 255,
                  "bgStartColorR": 255,
                  "capInsetsHeight": 1,
                  "capInsetsWidth": 1,
                  "capInsetsX": 0,
                  "capInsetsY": 0,
                  "clipAble": false,
                  "colorType": 1,
                  "layoutType": 0,
                  "vectorX": 0,
                  "vectorY": -0.5
                }
              },
              {
                "classname": "ImageView",
                "name": null,
                "children": [],
                "options": {
                  "__type": "ImageViewSurrogate:#EditorCommon.JsonModel.Component.GUI",
                  "classname": "ImageView",
                  "name": "Image_type",
                  "ZOrder": 0,
                  "actiontag": 64773780,
                  "anchorPointX": 0.5,
                  "anchorPointY": 0.5,
                  "classType": "CocoStudio.EngineAdapterWrap.CSImageView",
                  "colorB": 255,
                  "colorG": 255,
                  "colorR": 255,
                  "customProperty": "",
                  "flipX": false,
                  "flipY": false,
                  "height": 28,
                  "ignoreSize": true,
                  "layoutParameter": null,
                  "opacity": 255,
                  "positionPercentX": -0.210772827,
                  "positionPercentY": 0.09090909,
                  "positionType": 0,
                  "rotation": 0,
                  "scaleX": 0.799999952,
                  "scaleY": 0.799999952,
                  "sizePercentX": 0.112412177,
                  "sizePercentY": 0.25454545,
                  "sizeType": 0,
                  "tag": 1091937,
                  "touchAble": false,
                  "useMergedTexture": false,
                  "visible": true,
                  "width": 48,
                  "x": -90,
                  "y": 10,
                  "capInsetsHeight": 1,
                  "capInsetsWidth": 1,
                  "capInsetsX": 0,
                  "capInsetsY": 0,
                  "fileName": null,
                  "fileNameData": {
                    "path": "main/ico_common_shuxing_gong.png",
                    "plistFile": "",
                    "resourceType": 0
                  },
                  "scale9Enable": false,
                  "scale9Height": 28,
                  "scale9Width": 48
                }
              },
              {
                "classname": "Label",
                "name": null,
                "children": [],
                "options": {
                  "__type": "LabelSurrogate:#EditorCommon.JsonModel.Component.GUI",
                  "classname": "Label",
                  "name": "Label_name",
                  "ZOrder": 0,
                  "actiontag": 48821927,
                  "anchorPointX": 0,
                  "anchorPointY": 0.5,
                  "classType": "CocoStudio.EngineAdapterWrap.CSLabel",
                  "colorB": 12,
                  "colorG": 241,
                  "colorR": 255,
                  "customProperty": "",
                  "flipX": false,
                  "flipY": false,
                  "height": 16,
                  "ignoreSize": true,
                  "layoutParameter": null,
                  "opacity": 255,
                  "positionPercentX": -0.159250587,
                  "positionPercentY": 0.09090909,
                  "positionType": 0,
                  "rotation": 0,
                  "scaleX": 1,
                  "scaleY": 1,
                  "sizePercentX": 0.07494145,
                  "sizePercentY": 0.145454541,
                  "sizeType": 0,
                  "tag": 1089556,
                  "touchAble": false,
                  "useMergedTexture": false,
                  "visible": true,
                  "width": 32,
                  "x": -68,
                  "y": 10,
                  "areaHeight": 0,
                  "areaWidth": 0,
                  "fontFile": null,
                  "fontName": "static/FZCuYuan-M03S.ttf",
                  "fontSize": 16,
                  "hAlignment": 0,
                  "text": "名字",
                  "touchScaleEnable": false,
                  "vAlignment": 1
                }
              },
              {
                "classname": "Label",
                "name": null,
                "children": [],
                "options": {
                  "__type": "LabelSurrogate:#EditorCommon.JsonModel.Component.GUI",
                  "classname": "Label",
                  "name": "Label_cond",
                  "ZOrder": 0,
                  "actiontag": 11303480,
                  "anchorPointX": 0,
                  "anchorPointY": 0.5,
                  "classType": "CocoStudio.EngineAdapterWrap.CSLabel",
                  "colorB": 249,
                  "colorG": 255,
                  "colorR": 90,
                  "customProperty": "",
                  "flipX": false,
                  "flipY": false,
                  "height": 16,
                  "ignoreSize": true,
                  "layoutParameter": null,
                  "opacity": 255,
                  "positionPercentX": -0.2529274,
                  "positionPercentY": -0.163636357,
                  "positionType": 0,
                  "rotation": 0,
                  "scaleX": 1,
                  "scaleY": 1,
                  "sizePercentX": 0.187353626,
                  "sizePercentY": 0.145454541,
                  "sizeType": 0,
                  "tag": 1091646,
                  "touchAble": false,
                  "useMergedTexture": false,
                  "visible": true,
                  "width": 80,
                  "x": -108,
                  "y": -18,
                  "areaHeight": 0,
                  "areaWidth": 0,
                  "fontFile": null,
                  "fontName": "static/FZCuYuan-M03S.ttf",
                  "fontSize": 16,
                  "hAlignment": 0,
                  "text": "满足条件：",
                  "touchScaleEnable": false,
                  "vAlignment": 1
                }
              },
              {
                "classname": "Panel",
                "name": null,
                "children": [],
                "options": {
                  "__type": "PanelSurrogate:#EditorCommon.JsonModel.Component.GUI",
                  "classname": "Panel",
                  "name": "Panel_cond",
                  "ZOrder": 0,
                  "actiontag": 17400782,
                  "anchorPointX": 0,
                  "anchorPointY": 0,
                  "classType": "CocoStudio.EngineAdapterWrap.CSPanel",
                  "colorB": 255,
                  "colorG": 255,
                  "colorR": 255,
                  "customProperty": "",
                  "flipX": false,
                  "flipY": false,
                  "height": 20,
                  "ignoreSize": false,
                  "layoutParameter": null,
                  "opacity": 255,
                  "positionPercentX": -0.2529274,
                  "positionPercentY": -0.25454545,
                  "positionType": 0,
                  "rotation": 0,
                  "scaleX": 1,
                  "scaleY": 1,
                  "sizePercentX": 0.4683841,
                  "sizePercentY": 0.181818187,
                  "sizeType": 0,
                  "tag": 1091842,
                  "touchAble": true,
                  "useMergedTexture": false,
                  "visible": true,
                  "width": 200,
                  "x": -108,
                  "y": -28,
                  "adaptScreen": false,
                  "backGroundImage": null,
                  "backGroundImageData": null,
                  "backGroundScale9Enable": false,
                  "bgColorB": 255,
                  "bgColorG": 200,
                  "bgColorOpacity": 0,
                  "bgColorR": 150,
                  "bgEndColorB": 255,
                  "bgEndColorG": 200,
                  "bgEndColorR": 150,
                  "bgStartColorB": 255,
                  "bgStartColorG": 255,
                  "bgStartColorR": 255,
                  "capInsetsHeight": 1,
                  "capInsetsWidth": 1,
                  "capInsetsX": 0,
                  "capInsetsY": 0,
                  "clipAble": false,
                  "colorType": 1,
                  "layoutType": 0,
                  "vectorX": 0,
                  "vectorY": -0.5
                }
              },
              {
                "classname": "Button",
                "name": null,
                "children": [],
                "options": {
                  "__type": "ButtonSurrogate:#EditorCommon.JsonModel.Component.GUI",
                  "classname": "Button",
                  "name": "Button_up",
                  "ZOrder": 0,
                  "actiontag": 41028922,
                  "anchorPointX": 0.5,
                  "anchorPointY": 0.5,
                  "classType": "CocoStudio.EngineAdapterWrap.CSButton",
                  "colorB": 255,
                  "colorG": 255,
                  "colorR": 255,
                  "customProperty": "",
                  "flipX": false,
                  "flipY": false,
                  "height": 40,
                  "ignoreSize": true,
                  "layoutParameter": null,
                  "opacity": 255,
                  "positionPercentX": 0.334894627,
                  "positionPercentY": -0.0545454547,
                  "positionType": 0,
                  "rotation": 0,
                  "scaleX": 1,
                  "scaleY": 1,
                  "sizePercentX": 0.229508191,
                  "sizePercentY": 0.363636374,
                  "sizeType": 0,
                  "tag": 1089551,
                  "touchAble": true,
                  "useMergedTexture": false,
                  "visible": true,
                  "width": 98,
                  "x": 143,
                  "y": -6,
                  "capInsetsHeight": 1,
                  "capInsetsWidth": 1,
                  "capInsetsX": 0,
                  "capInsetsY": 0,
                  "disabled": null,
                  "disabledData": {
                    "path": "activity/X悬赏/切图/bth_xuanshang_tanchuang_shangzhen_normal.png",
                    "plistFile": "",
                    "resourceType": 0
                  },
                  "fontName": "微软雅黑",
                  "fontSize": 14,
                  "fontType": 0,
                  "normal": null,
                  "normalData": {
                    "path": "activity/X悬赏/切图/bth_xuanshang_tanchuang_shangzhen_normal.png",
                    "plistFile": "",
                    "resourceType": 0
                  },
                  "pressed": null,
                  "pressedData": {
                    "path": "activity/X悬赏/切图/bth_xuanshang_tanchuang_shangzhen_press.png",
                    "plistFile": "",
                    "resourceType": 0
                  },
                  "scale9Enable": false,
                  "scale9Height": 40,
                  "scale9Width": 98,
                  "text": "",
                  "textColorB": 255,
                  "textColorG": 255,
                  "textColorR": 255
                }
              },
              {
                "classname": "Button",
                "name": null,
                "children": [],
                "options": {
                  "__type": "ButtonSurrogate:#EditorCommon.JsonModel.Component.GUI",
                  "classname": "Button",
                  "name": "Button_down",
                  "ZOrder": 0,
                  "actiontag": 10295252,
                  "anchorPointX": 0.5,
                  "anchorPointY": 0.5,
                  "classType": "CocoStudio.EngineAdapterWrap.CSButton",
                  "colorB": 255,
                  "colorG": 255,
                  "colorR": 255,
                  "customProperty": "",
                  "flipX": false,
                  "flipY": false,
                  "height": 40,
                  "ignoreSize": true,
                  "layoutParameter": null,
                  "opacity": 255,
                  "positionPercentX": 0.334894627,
                  "positionPercentY": -0.0545454547,
                  "positionType": 0,
                  "rotation": 0,
                  "scaleX": 1,
                  "scaleY": 1,
                  "sizePercentX": 0.229508191,
                  "sizePercentY": 0.363636374,
                  "sizeType": 0,
                  "tag": 1091521,
                  "touchAble": true,
                  "useMergedTexture": false,
                  "visible": true,
                  "width": 98,
                  "x": 143,
                  "y": -6,
                  "capInsetsHeight": 1,
                  "capInsetsWidth": 1,
                  "capInsetsX": 0,
                  "capInsetsY": 0,
                  "disabled": null,
                  "disabledData": {
                    "path": "activity/X悬赏/切图/bth_xuanshang_tanchuang_xiazhen_normal.png",
                    "plistFile": "",
                    "resourceType": 0
                  },
                  "fontName": "微软雅黑",
                  "fontSize": 14,
                  "fontType": 0,
                  "normal": null,
                  "normalData": {
                    "path": "activity/X悬赏/切图/bth_xuanshang_tanchuang_xiazhen_normal.png",
                    "plistFile": "",
                    "resourceType": 0
                  },
                  "pressed": null,
                  "pressedData": {
                    "path": "activity/X悬赏/切图/bth_xuanshang_tanchuang_xiazhen_press.png",
                    "plistFile": "",
                    "resourceType": 0
                  },
                  "scale9Enable": false,
                  "scale9Height": 40,
                  "scale9Width": 98,
                  "text": "",
                  "textColorB": 255,
                  "textColorG": 255,
                  "textColorR": 255
                }
              },
              {
                "classname": "ImageView",
                "name": null,
                "children": [],
                "options": {
                  "__type": "ImageViewSurrogate:#EditorCommon.JsonModel.Component.GUI",
                  "classname": "ImageView",
                  "name": "Image_hasDispatch",
                  "ZOrder": 0,
                  "actiontag": 43595258,
                  "anchorPointX": 0.5,
                  "anchorPointY": 0.5,
                  "classType": "CocoStudio.EngineAdapterWrap.CSImageView",
                  "colorB": 255,
                  "colorG": 255,
                  "colorR": 255,
                  "customProperty": "",
                  "flipX": false,
                  "flipY": false,
                  "height": 36,
                  "ignoreSize": true,
                  "layoutParameter": null,
                  "opacity": 255,
                  "positionPercentX": 0.337236524,
                  "positionPercentY": -0.0454545468,
                  "positionType": 0,
                  "rotation": 0,
                  "scaleX": 1,
                  "scaleY": 1,
                  "sizePercentX": 0.220140517,
                  "sizePercentY": 0.3272727,
                  "sizeType": 0,
                  "tag": 1091522,
                  "touchAble": false,
                  "useMergedTexture": false,
                  "visible": true,
                  "width": 94,
                  "x": 144,
                  "y": -5,
                  "capInsetsHeight": 1,
                  "capInsetsWidth": 1,
                  "capInsetsX": 0,
                  "capInsetsY": 0,
                  "fileName": null,
                  "fileNameData": {
                    "path": "activity/X悬赏/切图/pic_xuanshang_tanchuang_yipaiqian.png",
                    "plistFile": "",
                    "resourceType": 0
                  },
                  "scale9Enable": false,
                  "scale9Height": 36,
                  "scale9Width": 94
                }
              }
            ],
            "options": {
              "__type": "ImageViewSurrogate:#EditorCommon.JsonModel.Component.GUI",
              "classname": "ImageView",
              "name": "Image_heroCell",
              "ZOrder": 2,
              "actiontag": 44981776,
              "anchorPointX": 0.5,
              "anchorPointY": 0.5,
              "classType": "CocoStudio.EngineAdapterWrap.CSImageView",
              "colorB": 255,
              "colorG": 255,
              "colorR": 255,
              "customProperty": "",
              "flipX": false,
              "flipY": false,
              "height": 110,
              "ignoreSize": true,
              "layoutParameter": null,
              "opacity": 255,
              "positionPercentX": -0.230434775,
              "positionPercentY": 0.103386812,
              "positionType": 0,
              "rotation": 0,
              "scaleX": 1,
              "scaleY": 1,
              "sizePercentX": 0.464130431,
              "sizePercentY": 0.196078435,
              "sizeType": 0,
              "tag": 1089542,
              "touchAble": false,
              "useMergedTexture": false,
              "visible": true,
              "width": 427,
              "x": -212,
              "y": 58,
              "capInsetsHeight": 6,
              "capInsetsWidth": 6,
              "capInsetsX": 50,
              "capInsetsY": 50,
              "fileName": null,
              "fileNameData": {
                "path": "activity/X悬赏/切图/pic_xuanshang_tanchuang_tiaomudi.png",
                "plistFile": "",
                "resourceType": 0
              },
              "scale9Enable": false,
              "scale9Height": 110,
              "scale9Width": 427
            }
          },
          {
            "classname": "ImageView",
            "name": null,
            "children": [
              {
                "classname": "ImageView",
                "name": null,
                "children": [],
                "options": {
                  "__type": "ImageViewSurrogate:#EditorCommon.JsonModel.Component.GUI",
                  "classname": "ImageView",
                  "name": "Image_notHaveHero",
                  "ZOrder": 0,
                  "actiontag": 56235574,
                  "anchorPointX": 0.5,
                  "anchorPointY": 0.5,
                  "classType": "CocoStudio.EngineAdapterWrap.CSImageView",
                  "colorB": 255,
                  "colorG": 255,
                  "colorR": 255,
                  "customProperty": "",
                  "flipX": false,
                  "flipY": false,
                  "height": 35,
                  "ignoreSize": true,
                  "layoutParameter": null,
                  "opacity": 255,
                  "positionPercentX": 0,
                  "positionPercentY": -0.106481485,
                  "positionType": 0,
                  "rotation": 0,
                  "scaleX": 1,
                  "scaleY": 1,
                  "sizePercentX": 0.569518745,
                  "sizePercentY": 0.16203703,
                  "sizeType": 0,
                  "tag": 1091841,
                  "touchAble": false,
                  "useMergedTexture": false,
                  "visible": true,
                  "width": 213,
                  "x": 0,
                  "y": -23,
                  "capInsetsHeight": 1,
                  "capInsetsWidth": 1,
                  "capInsetsX": 0,
                  "capInsetsY": 0,
                  "fileName": null,
                  "fileNameData": {
                    "path": "activity/X悬赏/切图/pic_xuanshang_zanwugedoujia.png",
                    "plistFile": "",
                    "resourceType": 0
                  },
                  "scale9Enable": false,
                  "scale9Height": 35,
                  "scale9Width": 213
                }
              }
            ],
            "options": {
              "__type": "ImageViewSurrogate:#EditorCommon.JsonModel.Component.GUI",
              "classname": "ImageView",
              "name": "Image_notHaveHeroBg",
              "ZOrder": 0,
              "actiontag": 34156745,
              "anchorPointX": 0.5,
              "anchorPointY": 0.5,
              "classType": "CocoStudio.EngineAdapterWrap.CSImageView",
              "colorB": 255,
              "colorG": 255,
              "colorR": 255,
              "customProperty": "",
              "flipX": false,
              "flipY": false,
              "height": 216,
              "ignoreSize": true,
              "layoutParameter": null,
              "opacity": 255,
              "positionPercentX": -0.229347825,
              "positionPercentY": 0.0142602492,
              "positionType": 0,
              "rotation": 0,
              "scaleX": 1,
              "scaleY": 1,
              "sizePercentX": 0.406521738,
              "sizePercentY": 0.385026723,
              "sizeType": 0,
              "tag": 1091840,
              "touchAble": false,
              "useMergedTexture": false,
              "visible": true,
              "width": 374,
              "x": -211,
              "y": 8,
              "capInsetsHeight": 1,
              "capInsetsWidth": 1,
              "capInsetsX": 0,
              "capInsetsY": 0,
              "fileName": null,
              "fileNameData": {
                "path": "activity/X悬赏/切图/pic_xuanshang_kongzhuangtai.png",
                "plistFile": "",
                "resourceType": 0
              },
              "scale9Enable": false,
              "scale9Height": 216,
              "scale9Width": 374
            }
          },
          {
            "classname": "ImageView",
            "name": null,
            "children": [
              {
                "classname": "ImageView",
                "name": null,
                "children": [
                  {
                    "classname": "ImageView",
                    "name": null,
                    "children": [],
                    "options": {
                      "__type": "ImageViewSurrogate:#EditorCommon.JsonModel.Component.GUI",
                      "classname": "ImageView",
                      "name": "Image_titleBorder",
                      "ZOrder": 0,
                      "actiontag": 25554779,
                      "anchorPointX": 0.5,
                      "anchorPointY": 0.5,
                      "classType": "CocoStudio.EngineAdapterWrap.CSImageView",
                      "colorB": 255,
                      "colorG": 255,
                      "colorR": 255,
                      "customProperty": "",
                      "flipX": false,
                      "flipY": false,
                      "height": 10,
                      "ignoreSize": true,
                      "layoutParameter": null,
                      "opacity": 255,
                      "positionPercentX": 0,
                      "positionPercentY": 0.334763944,
                      "positionType": 0,
                      "rotation": 0,
                      "scaleX": 1,
                      "scaleY": 1,
                      "sizePercentX": 0.7413793,
                      "sizePercentY": 0.0429184549,
                      "sizeType": 0,
                      "tag": 1091663,
                      "touchAble": false,
                      "useMergedTexture": false,
                      "visible": true,
                      "width": 301,
                      "x": 0,
                      "y": 78,
                      "capInsetsHeight": 1,
                      "capInsetsWidth": 1,
                      "capInsetsX": 0,
                      "capInsetsY": 0,
                      "fileName": null,
                      "fileNameData": {
                        "path": "activity/X悬赏/切图/pic_xuanshang_tanchuanghuawen.png",
                        "plistFile": "",
                        "resourceType": 0
                      },
                      "scale9Enable": false,
                      "scale9Height": 10,
                      "scale9Width": 301
                    }
                  }
                ],
                "options": {
                  "__type": "ImageViewSurrogate:#EditorCommon.JsonModel.Component.GUI",
                  "classname": "ImageView",
                  "name": "Image_upFrame",
                  "ZOrder": 0,
                  "actiontag": 2452053,
                  "anchorPointX": 0.5,
                  "anchorPointY": 0.5,
                  "classType": "CocoStudio.EngineAdapterWrap.CSImageView",
                  "colorB": 255,
                  "colorG": 255,
                  "colorR": 255,
                  "customProperty": "",
                  "flipX": false,
                  "flipY": false,
                  "height": 233,
                  "ignoreSize": false,
                  "layoutParameter": null,
                  "opacity": 255,
                  "positionPercentX": 0,
                  "positionPercentY": 0.218604654,
                  "positionType": 0,
                  "rotation": 0,
                  "scaleX": 1,
                  "scaleY": 1,
                  "sizePercentX": 0.9508197,
                  "sizePercentY": 0.541860461,
                  "sizeType": 0,
                  "tag": 1091659,
                  "touchAble": false,
                  "useMergedTexture": false,
                  "visible": true,
                  "width": 406,
                  "x": 0,
                  "y": 94,
                  "capInsetsHeight": 6,
                  "capInsetsWidth": 7,
                  "capInsetsX": 10,
                  "capInsetsY": 10,
                  "fileName": null,
                  "fileNameData": {
                    "path": "activity/X悬赏/切图/pic_xuanshang_tanchuangxiankuangjiugong.png",
                    "plistFile": "",
                    "resourceType": 0
                  },
                  "scale9Enable": true,
                  "scale9Height": 233,
                  "scale9Width": 406
                }
              },
              {
                "classname": "ImageView",
                "name": null,
                "children": [
                  {
                    "classname": "ImageView",
                    "name": null,
                    "children": [],
                    "options": {
                      "__type": "ImageViewSurrogate:#EditorCommon.JsonModel.Component.GUI",
                      "classname": "ImageView",
                      "name": "Image_titleBorder",
                      "ZOrder": 0,
                      "actiontag": 22138203,
                      "anchorPointX": 0.5,
                      "anchorPointY": 0.5,
                      "classType": "CocoStudio.EngineAdapterWrap.CSImageView",
                      "colorB": 255,
                      "colorG": 255,
                      "colorR": 255,
                      "customProperty": "",
                      "flipX": false,
                      "flipY": false,
                      "height": 10,
                      "ignoreSize": true,
                      "layoutParameter": null,
                      "opacity": 255,
                      "positionPercentX": 0,
                      "positionPercentY": 0.2826087,
                      "positionType": 0,
                      "rotation": 0,
                      "scaleX": 1,
                      "scaleY": 1,
                      "sizePercentX": 0.7413793,
                      "sizePercentY": 0.108695649,
                      "sizeType": 0,
                      "tag": 1091665,
                      "touchAble": false,
                      "useMergedTexture": false,
                      "visible": true,
                      "width": 301,
                      "x": 0,
                      "y": 26,
                      "capInsetsHeight": 1,
                      "capInsetsWidth": 1,
                      "capInsetsX": 0,
                      "capInsetsY": 0,
                      "fileName": null,
                      "fileNameData": {
                        "path": "activity/X悬赏/切图/pic_xuanshang_tanchuanghuawen.png",
                        "plistFile": "",
                        "resourceType": 0
                      },
                      "scale9Enable": false,
                      "scale9Height": 10,
                      "scale9Width": 301
                    }
                  },
                  {
                    "classname": "ImageView",
                    "name": null,
                    "children": [],
                    "options": {
                      "__type": "ImageViewSurrogate:#EditorCommon.JsonModel.Component.GUI",
                      "classname": "ImageView",
                      "name": "Image_line",
                      "ZOrder": 0,
                      "actiontag": 66352506,
                      "anchorPointX": 0.5,
                      "anchorPointY": 0.5,
                      "classType": "CocoStudio.EngineAdapterWrap.CSImageView",
                      "colorB": 255,
                      "colorG": 255,
                      "colorR": 255,
                      "customProperty": "",
                      "flipX": false,
                      "flipY": false,
                      "height": 8,
                      "ignoreSize": true,
                      "layoutParameter": null,
                      "opacity": 255,
                      "positionPercentX": 0,
                      "positionPercentY": -0.5217391,
                      "positionType": 0,
                      "rotation": 0,
                      "scaleX": 1,
                      "scaleY": 1,
                      "sizePercentX": 0.9729064,
                      "sizePercentY": 0.08695652,
                      "sizeType": 0,
                      "tag": 1091662,
                      "touchAble": false,
                      "useMergedTexture": false,
                      "visible": true,
                      "width": 395,
                      "x": 0,
                      "y": -48,
                      "capInsetsHeight": 1,
                      "capInsetsWidth": 1,
                      "capInsetsX": 0,
                      "capInsetsY": 0,
                      "fileName": null,
                      "fileNameData": {
                        "path": "activity/X悬赏/切图/pic_xuanshang_tanchuangfengexian.png",
                        "plistFile": "",
                        "resourceType": 0
                      },
                      "scale9Enable": false,
                      "scale9Height": 8,
                      "scale9Width": 395
                    }
                  }
                ],
                "options": {
                  "__type": "ImageViewSurrogate:#EditorCommon.JsonModel.Component.GUI",
                  "classname": "ImageView",
                  "name": "Image_downFrame",
                  "ZOrder": 0,
                  "actiontag": 33701535,
                  "anchorPointX": 0.5,
                  "anchorPointY": 0.5,
                  "classType": "CocoStudio.EngineAdapterWrap.CSImageView",
                  "colorB": 255,
                  "colorG": 255,
                  "colorR": 255,
                  "customProperty": "",
                  "flipX": false,
                  "flipY": false,
                  "height": 92,
                  "ignoreSize": false,
                  "layoutParameter": null,
                  "opacity": 255,
                  "positionPercentX": 0,
                  "positionPercentY": -0.1744186,
                  "positionType": 0,
                  "rotation": 0,
                  "scaleX": 1,
                  "scaleY": 1,
                  "sizePercentX": 0.9508197,
                  "sizePercentY": 0.2139535,
                  "sizeType": 0,
                  "tag": 1091661,
                  "touchAble": false,
                  "useMergedTexture": false,
                  "visible": true,
                  "width": 406,
                  "x": 0,
                  "y": -75,
                  "capInsetsHeight": 6,
                  "capInsetsWidth": 7,
                  "capInsetsX": 10,
                  "capInsetsY": 10,
                  "fileName": null,
                  "fileNameData": {
                    "path": "activity/X悬赏/切图/pic_xuanshang_tanchuangxiankuangjiugong.png",
                    "plistFile": "",
                    "resourceType": 0
                  },
                  "scale9Enable": true,
                  "scale9Height": 92,
                  "scale9Width": 406
                }
              }
            ],
            "options": {
              "__type": "ImageViewSurrogate:#EditorCommon.JsonModel.Component.GUI",
              "classname": "ImageView",
              "name": "Image_rightBg",
              "ZOrder": 0,
              "actiontag": 64963298,
              "anchorPointX": 0.5,
              "anchorPointY": 0.5,
              "classType": "CocoStudio.EngineAdapterWrap.CSImageView",
              "colorB": 255,
              "colorG": 255,
              "colorR": 255,
              "customProperty": "",
              "flipX": false,
              "flipY": false,
              "height": 430,
              "ignoreSize": true,
              "layoutParameter": null,
              "opacity": 255,
              "positionPercentX": 0.229347825,
              "positionPercentY": -0.017825311,
              "positionType": 0,
              "rotation": 0,
              "scaleX": 1,
              "scaleY": 1,
              "sizePercentX": 0.464130431,
              "sizePercentY": 0.766488433,
              "sizeType": 0,
              "tag": 1091666,
              "touchAble": false,
              "useMergedTexture": false,
              "visible": true,
              "width": 427,
              "x": 211,
              "y": -10,
              "capInsetsHeight": 1,
              "capInsetsWidth": 1,
              "capInsetsX": 0,
              "capInsetsY": 0,
              "fileName": null,
              "fileNameData": {
                "path": "activity/X悬赏/切图/pic_xuanshang_tanchuang_youdi.png",
                "plistFile": "",
                "resourceType": 0
              },
              "scale9Enable": false,
              "scale9Height": 430,
              "scale9Width": 427
            }
          },
          {
            "classname": "Label",
            "name": null,
            "children": [],
            "options": {
              "__type": "LabelSurrogate:#EditorCommon.JsonModel.Component.GUI",
              "classname": "Label",
              "name": "Label_times",
              "ZOrder": 0,
              "actiontag": 22548465,
              "anchorPointX": 0,
              "anchorPointY": 0.5,
              "classType": "CocoStudio.EngineAdapterWrap.CSLabel",
              "colorB": 249,
              "colorG": 255,
              "colorR": 90,
              "customProperty": "",
              "flipX": false,
              "flipY": false,
              "height": 16,
              "ignoreSize": true,
              "layoutParameter": null,
              "opacity": 255,
              "positionPercentX": 0.02173913,
              "positionPercentY": 0.33511585,
              "positionType": 0,
              "rotation": 0,
              "scaleX": 1,
              "scaleY": 1,
              "sizePercentX": 0.11304348,
              "sizePercentY": 0.0285204984,
              "sizeType": 0,
              "tag": 1091514,
              "touchAble": false,
              "useMergedTexture": false,
              "visible": true,
              "width": 104,
              "x": 20,
              "y": 188,
              "areaHeight": 0,
              "areaWidth": 0,
              "fontFile": null,
              "fontName": "static/FZCuYuan-M03S.ttf",
              "fontSize": 16,
              "hAlignment": 0,
              "text": "悬赏次数：3/3",
              "touchScaleEnable": false,
              "vAlignment": 1
            }
          },
          {
            "classname": "Label",
            "name": null,
            "children": [],
            "options": {
              "__type": "LabelSurrogate:#EditorCommon.JsonModel.Component.GUI",
              "classname": "Label",
              "name": "Label_taskTime",
              "ZOrder": 0,
              "actiontag": 29741910,
              "anchorPointX": 1,
              "anchorPointY": 0.5,
              "classType": "CocoStudio.EngineAdapterWrap.CSLabel",
              "colorB": 249,
              "colorG": 255,
              "colorR": 90,
              "customProperty": "",
              "flipX": false,
              "flipY": false,
              "height": 16,
              "ignoreSize": true,
              "layoutParameter": null,
              "opacity": 255,
              "positionPercentX": 0.4402174,
              "positionPercentY": 0.33511585,
              "positionType": 0,
              "rotation": 0,
              "scaleX": 1,
              "scaleY": 1,
              "sizePercentX": 0.104347825,
              "sizePercentY": 0.0285204984,
              "sizeType": 0,
              "tag": 1091516,
              "touchAble": false,
              "useMergedTexture": false,
              "visible": true,
              "width": 96,
              "x": 405,
              "y": 188,
              "areaHeight": 0,
              "areaWidth": 0,
              "fontFile": null,
              "fontName": "static/FZCuYuan-M03S.ttf",
              "fontSize": 16,
              "hAlignment": 2,
              "text": "任务时长：00",
              "touchScaleEnable": false,
              "vAlignment": 1
            }
          },
          {
            "classname": "Label",
            "name": null,
            "children": [],
            "options": {
              "__type": "LabelSurrogate:#EditorCommon.JsonModel.Component.GUI",
              "classname": "Label",
              "name": "Label_upCond",
              "ZOrder": 0,
              "actiontag": 30501168,
              "anchorPointX": 0.5,
              "anchorPointY": 0.5,
              "classType": "CocoStudio.EngineAdapterWrap.CSLabel",
              "colorB": 127,
              "colorG": 244,
              "colorR": 255,
              "customProperty": "",
              "flipX": false,
              "flipY": false,
              "height": 18,
              "ignoreSize": true,
              "layoutParameter": null,
              "opacity": 255,
              "positionPercentX": 0.229347825,
              "positionPercentY": 0.294117659,
              "positionType": 0,
              "rotation": 0,
              "scaleX": 1,
              "scaleY": 1,
              "sizePercentX": 0.07826087,
              "sizePercentY": 0.03208556,
              "sizeType": 0,
              "tag": 1091626,
              "touchAble": false,
              "useMergedTexture": false,
              "visible": true,
              "width": 72,
              "x": 211,
              "y": 165,
              "areaHeight": 0,
              "areaWidth": 0,
              "fontFile": null,
              "fontName": "static/FZCuYuan-M03S.ttf",
              "fontSize": 18,
              "hAlignment": 0,
              "text": "上阵条件",
              "touchScaleEnable": false,
              "vAlignment": 1
            }
          },
          {
            "classname": "Panel",
            "name": null,
            "children": [],
            "options": {
              "__type": "PanelSurrogate:#EditorCommon.JsonModel.Component.GUI",
              "classname": "Panel",
              "name": "Panel_hero",
              "ZOrder": 0,
              "actiontag": 6155739,
              "anchorPointX": 0,
              "anchorPointY": 0,
              "classType": "CocoStudio.EngineAdapterWrap.CSPanel",
              "colorB": 255,
              "colorG": 255,
              "colorR": 255,
              "customProperty": "",
              "flipX": false,
              "flipY": false,
              "height": 70,
              "ignoreSize": false,
              "layoutParameter": null,
              "opacity": 255,
              "positionPercentX": 0.0119565213,
              "positionPercentY": 0.130124778,
              "positionType": 0,
              "rotation": 0,
              "scaleX": 1,
              "scaleY": 1,
              "sizePercentX": 0.4347826,
              "sizePercentY": 0.124777183,
              "sizeType": 0,
              "tag": 1091517,
              "touchAble": true,
              "useMergedTexture": false,
              "visible": true,
              "width": 400,
              "x": 11,
              "y": 73,
              "adaptScreen": false,
              "backGroundImage": null,
              "backGroundImageData": null,
              "backGroundScale9Enable": false,
              "bgColorB": 5,
              "bgColorG": 27,
              "bgColorOpacity": 0,
              "bgColorR": 242,
              "bgEndColorB": 255,
              "bgEndColorG": 200,
              "bgEndColorR": 150,
              "bgStartColorB": 255,
              "bgStartColorG": 255,
              "bgStartColorR": 255,
              "capInsetsHeight": 1,
              "capInsetsWidth": 1,
              "capInsetsX": 0,
              "capInsetsY": 0,
              "clipAble": false,
              "colorType": 1,
              "layoutType": 0,
              "vectorX": 0,
              "vectorY": -0.5
            }
          },
          {
            "classname": "ImageView",
            "name": null,
            "children": [
              {
                "classname": "ImageView",
                "name": null,
                "children": [],
                "options": {
                  "__type": "ImageViewSurrogate:#EditorCommon.JsonModel.Component.GUI",
                  "classname": "ImageView",
                  "name": "Image_down",
                  "ZOrder": 5,
                  "actiontag": 309313,
                  "anchorPointX": 0.5,
                  "anchorPointY": 0.5,
                  "classType": "CocoStudio.EngineAdapterWrap.CSImageView",
                  "colorB": 255,
                  "colorG": 255,
                  "colorR": 255,
                  "customProperty": "",
                  "flipX": false,
                  "flipY": false,
                  "height": 19,
                  "ignoreSize": true,
                  "layoutParameter": null,
                  "opacity": 255,
                  "positionPercentX": 0.44262296,
                  "positionPercentY": 0.44262296,
                  "positionType": 0,
                  "rotation": 0,
                  "scaleX": 1,
                  "scaleY": 1,
                  "sizePercentX": 0.3114754,
                  "sizePercentY": 0.3114754,
                  "sizeType": 0,
                  "tag": 1091628,
                  "touchAble": false,
                  "useMergedTexture": false,
                  "visible": true,
                  "width": 19,
                  "x": 27,
                  "y": 27,
                  "capInsetsHeight": 1,
                  "capInsetsWidth": 1,
                  "capInsetsX": 0,
                  "capInsetsY": 0,
                  "fileName": null,
                  "fileNameData": {
                    "path": "activity/X悬赏/切图/pic_xuanshang_jianhao.png",
                    "plistFile": "",
                    "resourceType": 0
                  },
                  "scale9Enable": false,
                  "scale9Height": 19,
                  "scale9Width": 19
                }
              }
            ],
            "options": {
              "__type": "ImageViewSurrogate:#EditorCommon.JsonModel.Component.GUI",
              "classname": "ImageView",
              "name": "Image_heroHeadBg",
              "ZOrder": 0,
              "actiontag": 35086149,
              "anchorPointX": 0.5,
              "anchorPointY": 0.5,
              "classType": "CocoStudio.EngineAdapterWrap.CSImageView",
              "colorB": 255,
              "colorG": 255,
              "colorR": 255,
              "customProperty": "",
              "flipX": false,
              "flipY": false,
              "height": 61,
              "ignoreSize": true,
              "layoutParameter": null,
              "opacity": 255,
              "positionPercentX": 0.229347825,
              "positionPercentY": 0.192513362,
              "positionType": 0,
              "rotation": 0,
              "scaleX": 1,
              "scaleY": 1,
              "sizePercentX": 0.06630435,
              "sizePercentY": 0.108734407,
              "sizeType": 0,
              "tag": 1091627,
              "touchAble": false,
              "useMergedTexture": false,
              "visible": true,
              "width": 61,
              "x": 211,
              "y": 108,
              "capInsetsHeight": 1,
              "capInsetsWidth": 1,
              "capInsetsX": 0,
              "capInsetsY": 0,
              "fileName": null,
              "fileNameData": {
                "path": "activity/X悬赏/切图/pic_xuanshang_tanchuang_touxiangdi.png",
                "plistFile": "",
                "resourceType": 0
              },
              "scale9Enable": false,
              "scale9Height": 61,
              "scale9Width": 61
            }
          },
          {
            "classname": "Panel",
            "name": null,
            "children": [],
            "options": {
              "__type": "PanelSurrogate:#EditorCommon.JsonModel.Component.GUI",
              "classname": "Panel",
              "name": "Panel_condition",
              "ZOrder": 0,
              "actiontag": 60361902,
              "anchorPointX": 0,
              "anchorPointY": 0,
              "classType": "CocoStudio.EngineAdapterWrap.CSPanel",
              "colorB": 255,
              "colorG": 255,
              "colorR": 255,
              "customProperty": "",
              "flipX": false,
              "flipY": false,
              "height": 100,
              "ignoreSize": false,
              "layoutParameter": null,
              "opacity": 255,
              "positionPercentX": 0.0119565213,
              "positionPercentY": -0.0570409968,
              "positionType": 0,
              "rotation": 0,
              "scaleX": 1,
              "scaleY": 1,
              "sizePercentX": 0.4347826,
              "sizePercentY": 0.178253114,
              "sizeType": 0,
              "tag": 1091524,
              "touchAble": true,
              "useMergedTexture": false,
              "visible": true,
              "width": 400,
              "x": 11,
              "y": -32,
              "adaptScreen": false,
              "backGroundImage": null,
              "backGroundImageData": null,
              "backGroundScale9Enable": false,
              "bgColorB": 12,
              "bgColorG": 185,
              "bgColorOpacity": 0,
              "bgColorR": 240,
              "bgEndColorB": 255,
              "bgEndColorG": 200,
              "bgEndColorR": 150,
              "bgStartColorB": 255,
              "bgStartColorG": 255,
              "bgStartColorR": 255,
              "capInsetsHeight": 1,
              "capInsetsWidth": 1,
              "capInsetsX": 0,
              "capInsetsY": 0,
              "clipAble": false,
              "colorType": 1,
              "layoutType": 0,
              "vectorX": 0,
              "vectorY": -0.5
            }
          },
          {
            "classname": "ImageView",
            "name": null,
            "children": [
              {
                "classname": "ImageView",
                "name": null,
                "children": [],
                "options": {
                  "__type": "ImageViewSurrogate:#EditorCommon.JsonModel.Component.GUI",
                  "classname": "ImageView",
                  "name": "Image_extra",
                  "ZOrder": 0,
                  "actiontag": 28332814,
                  "anchorPointX": 0.5,
                  "anchorPointY": 0.5,
                  "classType": "CocoStudio.EngineAdapterWrap.CSImageView",
                  "colorB": 255,
                  "colorG": 255,
                  "colorR": 255,
                  "customProperty": "",
                  "flipX": false,
                  "flipY": false,
                  "height": 27,
                  "ignoreSize": true,
                  "layoutParameter": null,
                  "opacity": 255,
                  "positionPercentX": -0.414507776,
                  "positionPercentY": 0,
                  "positionType": 0,
                  "rotation": 0,
                  "scaleX": 1,
                  "scaleY": 1,
                  "sizePercentX": 0.106217615,
                  "sizePercentY": 1,
                  "sizeType": 0,
                  "tag": 1091636,
                  "touchAble": false,
                  "useMergedTexture": false,
                  "visible": true,
                  "width": 41,
                  "x": -160,
                  "y": 0,
                  "capInsetsHeight": 1,
                  "capInsetsWidth": 1,
                  "capInsetsX": 0,
                  "capInsetsY": 0,
                  "fileName": null,
                  "fileNameData": {
                    "path": "activity/X悬赏/切图/pic_xuanshang_zhujiemian_ewai.png",
                    "plistFile": "",
                    "resourceType": 0
                  },
                  "scale9Enable": false,
                  "scale9Height": 27,
                  "scale9Width": 41
                }
              },
              {
                "classname": "ImageView",
                "name": null,
                "children": [],
                "options": {
                  "__type": "ImageViewSurrogate:#EditorCommon.JsonModel.Component.GUI",
                  "classname": "ImageView",
                  "name": "Image_condType",
                  "ZOrder": 0,
                  "actiontag": 66155960,
                  "anchorPointX": 0.5,
                  "anchorPointY": 0.5,
                  "classType": "CocoStudio.EngineAdapterWrap.CSImageView",
                  "colorB": 255,
                  "colorG": 255,
                  "colorR": 255,
                  "customProperty": "",
                  "flipX": false,
                  "flipY": false,
                  "height": 25,
                  "ignoreSize": true,
                  "layoutParameter": null,
                  "opacity": 255,
                  "positionPercentX": -0.316062182,
                  "positionPercentY": 0,
                  "positionType": 0,
                  "rotation": 0,
                  "scaleX": 1,
                  "scaleY": 1,
                  "sizePercentX": 0.06476684,
                  "sizePercentY": 0.9259259,
                  "sizeType": 0,
                  "tag": 1091639,
                  "touchAble": false,
                  "useMergedTexture": false,
                  "visible": true,
                  "width": 25,
                  "x": -122,
                  "y": 0,
                  "capInsetsHeight": 1,
                  "capInsetsWidth": 1,
                  "capInsetsX": 0,
                  "capInsetsY": 0,
                  "fileName": null,
                  "fileNameData": {
                    "path": "activity/X悬赏/切图/pic_xuanshang_tanchuang_lanse.png",
                    "plistFile": "",
                    "resourceType": 0
                  },
                  "scale9Enable": false,
                  "scale9Height": 25,
                  "scale9Width": 25
                }
              },
              {
                "classname": "Panel",
                "name": null,
                "children": [
                  {
                    "classname": "Label",
                    "name": null,
                    "children": [],
                    "options": {
                      "__type": "LabelSurrogate:#EditorCommon.JsonModel.Component.GUI",
                      "classname": "Label",
                      "name": "Label_condDesc",
                      "ZOrder": 0,
                      "actiontag": 11324876,
                      "anchorPointX": 0,
                      "anchorPointY": 0.5,
                      "classType": "CocoStudio.EngineAdapterWrap.CSLabel",
                      "colorB": 249,
                      "colorG": 255,
                      "colorR": 90,
                      "customProperty": "",
                      "flipX": false,
                      "flipY": false,
                      "height": 16,
                      "ignoreSize": true,
                      "layoutParameter": null,
                      "opacity": 255,
                      "positionPercentX": 1.05252738E-07,
                      "positionPercentY": 0.5,
                      "positionType": 0,
                      "rotation": 0,
                      "scaleX": 1,
                      "scaleY": 1,
                      "sizePercentX": 0.25,
                      "sizePercentY": 0.6666667,
                      "sizeType": 0,
                      "tag": 1091644,
                      "touchAble": false,
                      "useMergedTexture": false,
                      "visible": true,
                      "width": 64,
                      "x": 0,
                      "y": 12,
                      "areaHeight": 0,
                      "areaWidth": 0,
                      "fontFile": null,
                      "fontName": "static/FZCuYuan-M03S.ttf",
                      "fontSize": 16,
                      "hAlignment": 0,
                      "text": "任务条件",
                      "touchScaleEnable": false,
                      "vAlignment": 1
                    }
                  }
                ],
                "options": {
                  "__type": "PanelSurrogate:#EditorCommon.JsonModel.Component.GUI",
                  "classname": "Panel",
                  "name": "Panel_condDesc",
                  "ZOrder": 0,
                  "actiontag": 25908080,
                  "anchorPointX": 0,
                  "anchorPointY": 0,
                  "classType": "CocoStudio.EngineAdapterWrap.CSPanel",
                  "colorB": 255,
                  "colorG": 255,
                  "colorR": 255,
                  "customProperty": "",
                  "flipX": false,
                  "flipY": false,
                  "height": 24,
                  "ignoreSize": false,
                  "layoutParameter": null,
                  "opacity": 255,
                  "positionPercentX": -0.2823835,
                  "positionPercentY": -0.444444448,
                  "positionType": 0,
                  "rotation": 0,
                  "scaleX": 1,
                  "scaleY": 1,
                  "sizePercentX": 0.6632124,
                  "sizePercentY": 0.8888889,
                  "sizeType": 0,
                  "tag": 1092015,
                  "touchAble": true,
                  "useMergedTexture": false,
                  "visible": true,
                  "width": 256,
                  "x": -109,
                  "y": -12,
                  "adaptScreen": false,
                  "backGroundImage": null,
                  "backGroundImageData": null,
                  "backGroundScale9Enable": false,
                  "bgColorB": 255,
                  "bgColorG": 200,
                  "bgColorOpacity": 0,
                  "bgColorR": 150,
                  "bgEndColorB": 255,
                  "bgEndColorG": 200,
                  "bgEndColorR": 150,
                  "bgStartColorB": 255,
                  "bgStartColorG": 255,
                  "bgStartColorR": 255,
                  "capInsetsHeight": 1,
                  "capInsetsWidth": 1,
                  "capInsetsX": 0,
                  "capInsetsY": 0,
                  "clipAble": true,
                  "colorType": 1,
                  "layoutType": 0,
                  "vectorX": 0,
                  "vectorY": -0.5
                }
              },
              {
                "classname": "ImageView",
                "name": null,
                "children": [
                  {
                    "classname": "ImageView",
                    "name": null,
                    "children": [],
                    "options": {
                      "__type": "ImageViewSurrogate:#EditorCommon.JsonModel.Component.GUI",
                      "classname": "ImageView",
                      "name": "Image_result",
                      "ZOrder": 0,
                      "actiontag": 5836994,
                      "anchorPointX": 0.5,
                      "anchorPointY": 0.5,
                      "classType": "CocoStudio.EngineAdapterWrap.CSImageView",
                      "colorB": 255,
                      "colorG": 255,
                      "colorR": 255,
                      "customProperty": "",
                      "flipX": false,
                      "flipY": false,
                      "height": 28,
                      "ignoreSize": true,
                      "layoutParameter": null,
                      "opacity": 255,
                      "positionPercentX": 0,
                      "positionPercentY": 0,
                      "positionType": 0,
                      "rotation": 0,
                      "scaleX": 1,
                      "scaleY": 1,
                      "sizePercentX": 1.36363637,
                      "sizePercentY": 1.27272725,
                      "sizeType": 0,
                      "tag": 1091640,
                      "touchAble": false,
                      "useMergedTexture": false,
                      "visible": true,
                      "width": 30,
                      "x": 0,
                      "y": 0,
                      "capInsetsHeight": 1,
                      "capInsetsWidth": 1,
                      "capInsetsX": 0,
                      "capInsetsY": 0,
                      "fileName": null,
                      "fileNameData": {
                        "path": "activity/X悬赏/切图/pic_xuanshang_duigou.png",
                        "plistFile": "",
                        "resourceType": 0
                      },
                      "scale9Enable": false,
                      "scale9Height": 28,
                      "scale9Width": 30
                    }
                  }
                ],
                "options": {
                  "__type": "ImageViewSurrogate:#EditorCommon.JsonModel.Component.GUI",
                  "classname": "ImageView",
                  "name": "Image_resultBg",
                  "ZOrder": 0,
                  "actiontag": 16940088,
                  "anchorPointX": 0.5,
                  "anchorPointY": 0.5,
                  "classType": "CocoStudio.EngineAdapterWrap.CSImageView",
                  "colorB": 255,
                  "colorG": 255,
                  "colorR": 255,
                  "customProperty": "",
                  "flipX": false,
                  "flipY": false,
                  "height": 22,
                  "ignoreSize": true,
                  "layoutParameter": null,
                  "opacity": 255,
                  "positionPercentX": 0.4222798,
                  "positionPercentY": 0,
                  "positionType": 0,
                  "rotation": 0,
                  "scaleX": 1,
                  "scaleY": 1,
                  "sizePercentX": 0.05699482,
                  "sizePercentY": 0.8148148,
                  "sizeType": 0,
                  "tag": 1091642,
                  "touchAble": false,
                  "useMergedTexture": false,
                  "visible": true,
                  "width": 22,
                  "x": 163,
                  "y": 0,
                  "capInsetsHeight": 1,
                  "capInsetsWidth": 1,
                  "capInsetsX": 0,
                  "capInsetsY": 0,
                  "fileName": null,
                  "fileNameData": {
                    "path": "activity/X悬赏/切图/pic_xuanshang_yuandi.png",
                    "plistFile": "",
                    "resourceType": 0
                  },
                  "scale9Enable": false,
                  "scale9Height": 22,
                  "scale9Width": 22
                }
              }
            ],
            "options": {
              "__type": "ImageViewSurrogate:#EditorCommon.JsonModel.Component.GUI",
              "classname": "ImageView",
              "name": "Image_conditionCell",
              "ZOrder": 0,
              "actiontag": 44740824,
              "anchorPointX": 0.5,
              "anchorPointY": 0.5,
              "classType": "CocoStudio.EngineAdapterWrap.CSImageView",
              "colorB": 255,
              "colorG": 255,
              "colorR": 255,
              "customProperty": "",
              "flipX": false,
              "flipY": false,
              "height": 27,
              "ignoreSize": true,
              "layoutParameter": null,
              "opacity": 255,
              "positionPercentX": 0.229347825,
              "positionPercentY": 0.09269162,
              "positionType": 0,
              "rotation": 0,
              "scaleX": 1,
              "scaleY": 1,
              "sizePercentX": 0.419565231,
              "sizePercentY": 0.04812834,
              "sizeType": 0,
              "tag": 1091637,
              "touchAble": false,
              "useMergedTexture": false,
              "visible": true,
              "width": 386,
              "x": 211,
              "y": 52,
              "capInsetsHeight": 1,
              "capInsetsWidth": 1,
              "capInsetsX": 0,
              "capInsetsY": 0,
              "fileName": null,
              "fileNameData": {
                "path": "activity/X悬赏/切图/pic_xuanshang_zhujiemian_shangzhendilan.png",
                "plistFile": "",
                "resourceType": 0
              },
              "scale9Enable": false,
              "scale9Height": 27,
              "scale9Width": 386
            }
          },
          {
            "classname": "Panel",
            "name": null,
            "children": [
              {
                "classname": "Label",
                "name": null,
                "children": [],
                "options": {
                  "__type": "LabelSurrogate:#EditorCommon.JsonModel.Component.GUI",
                  "classname": "Label",
                  "name": "Label_reward",
                  "ZOrder": 0,
                  "actiontag": 36591224,
                  "anchorPointX": 0.5,
                  "anchorPointY": 0.5,
                  "classType": "CocoStudio.EngineAdapterWrap.CSLabel",
                  "colorB": 127,
                  "colorG": 244,
                  "colorR": 255,
                  "customProperty": "",
                  "flipX": false,
                  "flipY": false,
                  "height": 18,
                  "ignoreSize": true,
                  "layoutParameter": null,
                  "opacity": 255,
                  "positionPercentX": 0.5,
                  "positionPercentY": 0.844444454,
                  "positionType": 0,
                  "rotation": 0,
                  "scaleX": 1,
                  "scaleY": 1,
                  "sizePercentX": 0.09,
                  "sizePercentY": 0.2,
                  "sizeType": 0,
                  "tag": 1091630,
                  "touchAble": false,
                  "useMergedTexture": false,
                  "visible": true,
                  "width": 36,
                  "x": 200,
                  "y": 76,
                  "areaHeight": 0,
                  "areaWidth": 0,
                  "fontFile": null,
                  "fontName": "static/FZCuYuan-M03S.ttf",
                  "fontSize": 18,
                  "hAlignment": 1,
                  "text": "奖励",
                  "touchScaleEnable": false,
                  "vAlignment": 1
                }
              }
            ],
            "options": {
              "__type": "PanelSurrogate:#EditorCommon.JsonModel.Component.GUI",
              "classname": "Panel",
              "name": "Panel_reward",
              "ZOrder": 0,
              "actiontag": 43512323,
              "anchorPointX": 0,
              "anchorPointY": 0,
              "classType": "CocoStudio.EngineAdapterWrap.CSPanel",
              "colorB": 255,
              "colorG": 255,
              "colorR": 255,
              "customProperty": "",
              "flipX": false,
              "flipY": false,
              "height": 90,
              "ignoreSize": false,
              "layoutParameter": null,
              "opacity": 255,
              "positionPercentX": 0.0119565213,
              "positionPercentY": -0.235294119,
              "positionType": 0,
              "rotation": 0,
              "scaleX": 1,
              "scaleY": 1,
              "sizePercentX": 0.4347826,
              "sizePercentY": 0.160427809,
              "sizeType": 0,
              "tag": 1091519,
              "touchAble": true,
              "useMergedTexture": false,
              "visible": true,
              "width": 400,
              "x": 11,
              "y": -132,
              "adaptScreen": false,
              "backGroundImage": null,
              "backGroundImageData": null,
              "backGroundScale9Enable": false,
              "bgColorB": 11,
              "bgColorG": 88,
              "bgColorOpacity": 0,
              "bgColorR": 242,
              "bgEndColorB": 255,
              "bgEndColorG": 200,
              "bgEndColorR": 150,
              "bgStartColorB": 255,
              "bgStartColorG": 255,
              "bgStartColorR": 255,
              "capInsetsHeight": 1,
              "capInsetsWidth": 1,
              "capInsetsX": 0,
              "capInsetsY": 0,
              "clipAble": false,
              "colorType": 1,
              "layoutType": 0,
              "vectorX": 0,
              "vectorY": -0.5
            }
          },
          {
            "classname": "Button",
            "name": null,
            "children": [],
            "options": {
              "__type": "ButtonSurrogate:#EditorCommon.JsonModel.Component.GUI",
              "classname": "Button",
              "name": "Button_dispatch",
              "ZOrder": 0,
              "actiontag": 37852362,
              "anchorPointX": 0.5,
              "anchorPointY": 0.5,
              "classType": "CocoStudio.EngineAdapterWrap.CSButton",
              "colorB": 255,
              "colorG": 255,
              "colorR": 255,
              "customProperty": "",
              "flipX": false,
              "flipY": false,
              "height": 43,
              "ignoreSize": true,
              "layoutParameter": null,
              "opacity": 255,
              "positionPercentX": 0.131521747,
              "positionPercentY": -0.317290545,
              "positionType": 0,
              "rotation": 0,
              "scaleX": 1,
              "scaleY": 1,
              "sizePercentX": 0.130434781,
              "sizePercentY": 0.07664884,
              "sizeType": 0,
              "tag": 1090706,
              "touchAble": true,
              "useMergedTexture": false,
              "visible": true,
              "width": 120,
              "x": 121,
              "y": -178,
              "capInsetsHeight": 1,
              "capInsetsWidth": 1,
              "capInsetsX": 0,
              "capInsetsY": 0,
              "disabled": null,
              "disabledData": {
                "path": "activity/X悬赏/切图/bth_xuanshang_tanchuang_paiqian_normal.png",
                "plistFile": "",
                "resourceType": 0
              },
              "fontName": "微软雅黑",
              "fontSize": 14,
              "fontType": 0,
              "normal": null,
              "normalData": {
                "path": "activity/X悬赏/切图/bth_xuanshang_tanchuang_paiqian_normal.png",
                "plistFile": "",
                "resourceType": 0
              },
              "pressed": null,
              "pressedData": {
                "path": "activity/X悬赏/切图/bth_xuanshang_tanchuang_paiqian_press.png",
                "plistFile": "",
                "resourceType": 0
              },
              "scale9Enable": false,
              "scale9Height": 43,
              "scale9Width": 120,
              "text": "",
              "textColorB": 255,
              "textColorG": 255,
              "textColorR": 255
            }
          },
          {
            "classname": "Button",
            "name": null,
            "children": [],
            "options": {
              "__type": "ButtonSurrogate:#EditorCommon.JsonModel.Component.GUI",
              "classname": "Button",
              "name": "Button_onekeyDispatch",
              "ZOrder": 0,
              "actiontag": 5126940,
              "anchorPointX": 0.5,
              "anchorPointY": 0.5,
              "classType": "CocoStudio.EngineAdapterWrap.CSButton",
              "colorB": 255,
              "colorG": 255,
              "colorR": 255,
              "customProperty": "",
              "flipX": false,
              "flipY": false,
              "height": 43,
              "ignoreSize": true,
              "layoutParameter": null,
              "opacity": 255,
              "positionPercentX": 0.33369565,
              "positionPercentY": -0.317290545,
              "positionType": 0,
              "rotation": 0,
              "scaleX": 1,
              "scaleY": 1,
              "sizePercentX": 0.130434781,
              "sizePercentY": 0.07664884,
              "sizeType": 0,
              "tag": 1090707,
              "touchAble": true,
              "useMergedTexture": false,
              "visible": true,
              "width": 120,
              "x": 307,
              "y": -178,
              "capInsetsHeight": 1,
              "capInsetsWidth": 1,
              "capInsetsX": 0,
              "capInsetsY": 0,
              "disabled": null,
              "disabledData": {
                "path": "activity/X悬赏/切图/bth_xuanshang_tanchuang_yijianlingqu_normal.png",
                "plistFile": "",
                "resourceType": 0
              },
              "fontName": "微软雅黑",
              "fontSize": 14,
              "fontType": 0,
              "normal": null,
              "normalData": {
                "path": "activity/X悬赏/切图/bth_xuanshang_tanchuang_yijianlingqu_normal.png",
                "plistFile": "",
                "resourceType": 0
              },
              "pressed": null,
              "pressedData": {
                "path": "activity/X悬赏/切图/bth_xuanshang_tanchuang_yijianlingqu_press.png",
                "plistFile": "",
                "resourceType": 0
              },
              "scale9Enable": false,
              "scale9Height": 43,
              "scale9Width": 120,
              "text": "",
              "textColorB": 255,
              "textColorG": 255,
              "textColorR": 255
            }
          }
        ],
        "options": {
          "__type": "ImageViewSurrogate:#EditorCommon.JsonModel.Component.GUI",
          "classname": "ImageView",
          "name": "Image_bg",
          "ZOrder": 1,
          "actiontag": 64235856,
          "anchorPointX": 0.5,
          "anchorPointY": 0.5,
          "classType": "CocoStudio.EngineAdapterWrap.CSImageView",
          "colorB": 255,
          "colorG": 255,
          "colorR": 255,
          "customProperty": "",
          "flipX": false,
          "flipY": false,
          "height": 561,
          "ignoreSize": true,
          "layoutParameter": {
            "classname": null,
            "name": null,
            "align": 5,
            "gravity": 0,
            "layoutEageType": 0,
            "layoutNormalHorizontal": 0,
            "layoutNormalVertical": 0,
            "layoutParentHorizontal": 0,
            "layoutParentVertical": 0,
            "marginDown": 0,
            "marginLeft": 0,
            "marginRight": 0,
            "marginTop": 0,
            "relativeName": "Image_bg",
            "relativeToName": "root",
            "type": 2
          },
          "opacity": 255,
          "positionPercentX": 0.5,
          "positionPercentY": 0.5,
          "positionType": 0,
          "rotation": 0,
          "scaleX": 1,
          "scaleY": 1,
          "sizePercentX": 0.809859157,
          "sizePercentY": 0.8765625,
          "sizeType": 0,
          "tag": 1090702,
          "touchAble": false,
          "useMergedTexture": false,
          "visible": true,
          "width": 920,
          "x": 568,
          "y": 320,
          "capInsetsHeight": 1,
          "capInsetsWidth": 1,
          "capInsetsX": 0,
          "capInsetsY": 0,
          "fileName": null,
          "fileNameData": {
            "path": "activity/X悬赏/切图/pic_xuanshang_erjitanchuang_di.png",
            "plistFile": "",
            "resourceType": 0
          },
          "scale9Enable": false,
          "scale9Height": 561,
          "scale9Width": 920
        }
      }
    ],
    "options": {
      "__type": "PanelSurrogate:#EditorCommon.JsonModel.Component.GUI",
      "classname": "Panel",
      "name": "root",
      "ZOrder": 0,
      "actiontag": -1,
      "anchorPointX": 0,
      "anchorPointY": 0,
      "classType": "CocoStudio.EngineAdapterWrap.CSPanel",
      "colorB": 255,
      "colorG": 255,
      "colorR": 255,
      "customProperty": "",
      "flipX": false,
      "flipY": false,
      "height": 640,
      "ignoreSize": false,
      "layoutParameter": null,
      "opacity": 255,
      "positionPercentX": 0,
      "positionPercentY": 0,
      "positionType": 0,
      "rotation": 0,
      "scaleX": 1,
      "scaleY": 1,
      "sizePercentX": 1,
      "sizePercentY": 1,
      "sizeType": 0,
      "tag": 1088509,
      "touchAble": true,
      "useMergedTexture": false,
      "visible": true,
      "width": 1136,
      "x": 0,
      "y": 0,
      "adaptScreen": true,
      "backGroundImage": null,
      "backGroundImageData": null,
      "backGroundScale9Enable": false,
      "bgColorB": 255,
      "bgColorG": 200,
      "bgColorOpacity": 0,
      "bgColorR": 150,
      "bgEndColorB": 255,
      "bgEndColorG": 200,
      "bgEndColorR": 150,
      "bgStartColorB": 255,
      "bgStartColorG": 255,
      "bgStartColorR": 255,
      "capInsetsHeight": 1,
      "capInsetsWidth": 1,
      "capInsetsX": 0,
      "capInsetsY": 0,
      "clipAble": false,
      "colorType": 1,
      "layoutType": 3,
      "vectorX": 0,
      "vectorY": -0.5
    }
  }
}